{"url": "https://thanhnien.vn/suc-khoe/benh-vien-khong-thu-tam-ung-vien-phi-benh-nhan-cap-cuu-898284.html", "title": "Bệnh viện không thu tạm ứng viện phí bệnh nhân cấp cứu", "description": "Ngày 8 11  Ban Văn hóa - Xã hội (HĐND TP HCM) làm việc với Bệnh viện (BV) Nhân dân Gia Định về công tác khám  chữa bệnh bảo hiểm y tế cho người dân trên địa bàn TP ", "time": "2017-11-09 10:01:00", "content": "Tại buổi làm việc  TS-BS Nguyễn Anh Dũng  Giám đốc BV Nhân dân Gia Định  cho biết BV không thu tiền tạm ứng đối với bệnh nhân đến khám và điều trị ngoại trú  đặc biệt là bệnh nhân cấp cứu cần phải can thiệp điều trị bằng kỹ thuật cao có chi phí lớn   Với bệnh nhân nội trú  BV chỉ thu tạm ứng khi có chỉ định sử dụng kỹ thuật điều trị chi phí cao  nhưng cũng chỉ thu tạm ứng ngoài phần thanh toán của bảo hiểm y tế   Tuy nhiên  BV cũng kiến nghị TP nên nghiên cứu và đề xuất giải pháp hỗ trợ kinh phí sau khi BV đã sử dụng các kỹ thuật cao để điều trị cấp cứu và đã cứu sống bệnh nhân nhưng người bệnh không có khả năng chi trả…  tin liên quan Bác sĩ vừa cấp cứu mẹ  vừa chăm sóc 2 con của sản phụ Chuyện hy hữu này vừa xảy ra tại Bệnh viện (BV) Nhân dân Gia Định TP HCM tin liên quan Cứu sống du khách Pháp bị tắc mạch vành  ngưng tim  ngưng thở Các y bác sĩ của Bệnh viện T Ư Huế vừa cứu sống một bệnh nhân là du khách người Pháp  bị tắc mạch vành  nhập viện trong tình trạng ngưng tim  ngưng thở  tụt huyết áp  "}