{"url": "http://dantri.com.vn/xa-hoi/di-chuyen-the-nao-nhung-ngay-ha-noi-don-2-nguyen-thu-donald-trump-va-tap-can-binh-20171107110929591.htm", "title": "     Di chuyển thế nào những ngày Hà Nội đón 2 nguyên thủ Tập Cận Bình và Donald Trump ", "description": "     Di chuyển thế nào những ngày Hà Nội đón 2 nguyên thủ Tập Cận Bình và Donald Trump ", "time": "2017-11-07 11:14:00", "content": " Theo đó  trong các ngày 8  9  11  12  13 tháng 11  trên địa bàn Hà Nội diễn ra một số hoạt động của năm APEC 2017  đón 4 nguyên thủ các nền kinh tế sang thăm chính thức Việt Nam  trong đó có Tổng thống Hoa Kỳ Donald Trump và Tổng Bí thư Trung Quốc Tập Cận Bình  Để đảm bảo an ninh  an toàn và giao thông thông suốt  Công an TP Hà Nội thông báo phân luồng giao thông và tổ chức hướng đi cho các loại phương tiện  Cụ thể  từ 9h đến 22h các ngày 8  9  11  12  13 tháng 11  hạn chế đối với các xe ô tô chở hàng có khối lượng hàng hóa chuyên chở từ 500 kg trở lên  xe ô tô chở khách  xe taxi  xe ô tô cá nhân  xe mô tô (trừ các xe có phù hiệu bảo vệ  xe buýt  xe vệ sinh và xe giải quyết  khắc phục sự cố  xe chở khách tuyến cố định)  hoạt động trên một số tuyến đường  cụ thể như sau  Hạn chế phương tiện hoạt động trên địa bàn như sau  quận Hoàn Kiếm gồm các tuyến đường  Trần Nhật Duật  Trần Quang Khải  Tràng Tiền  Ngô Quyền  Quán Sứ  Tràng Thi  Hai Bà Trưng  Bà Triệu  Lý Thường Kiệt  Hàng Bài  Đinh Tiên Hoàng  Hàng Khay  Lê Thái Tổ  Đê 401  Quận Ba Đình  Tây Hồ gồm các tuyến đường  Điện Biên Phủ  Độc Lập  Hoàng Văn Thụ  Hoàng Diệu  Hùng Vương  Nam Hùng Vương  Lê Hồng Phong  Trần Phú  Kim Mã  An Dương Vương  Âu Cơ  Nghi Tàm  Yên Phụ  Vành đai II  Võ Chí Công  Quận Đống Đa gồm các tuyến đường  Nguyễn Chí Thanh  Chùa Láng  Láng  huyện Đông Anh  Sóc Sơn  đường Võ Nguyên Giáp  Các phương tiện vào trung tâm thành phố hạn chế đi qua địa bàn các quận Hoàn Kiếm  Ba Đình  Tây Hồ  Đống Đa  cầu Chương Dương  Nhật Tân (theo hướng vào trung tâm Thành phố)  Các phương tiện đi từ các tỉnh phía Đông thành phố (Quảng Ninh  Hải Dương  Thái Bình  Hưng Yên…) đi các tỉnh phía Bắc (Lào Cai  Vĩnh Phúc…) hoặc các tỉnh phía Tây thành phố (Phú Thọ  Hòa Bình  Sơn La  Điện Biên…) và ngược lại  Đi các tỉnh phía Bắc thành phố (Lào Cai  Vĩnh Phúc…)  Quốc lộ 5 - Lý Sơn - cầu Đông Trù - Trường Sa - Hoàng Sa - Võ Văn Kiệt đi các tỉnh  Đi các tỉnh phía Tây thành phố (Phú Thọ  Hòa Bình  Sơn La  Điện Biên…)  QL5 - QL1 - cầu Thanh Trì - Vành đai III trên cao - Đại lộ Thăng Long (hoặc QL32) hoặc theo tuyến  QL5 - Lý Sơn - cầu Đông Trù - Trường Sa - Hoàng Sa - Võ Văn Kiệt - cầu Thăng Long - Phạm Văn Đồng - Vành đai III - Đại lộ Thăng Long (hoặc từ Phạm Văn Đồng đi QL32) đi các tỉnh  Các phương tiện đi từ phía Nam thành phố (Nam Định  Hà Nam  Ninh Bình…) đi các tỉnh phía Bắc (Lào Cai  Vĩnh Phúc…) hoặc các tỉnh phía Tây thành phố (Phú Thọ  Hòa Bình  Sơn La  Điện Biên…) theo các hướng  Đi các tỉnh phía Bắc thành phố (Lào Cai  Vĩnh Phúc…)  Pháp Vân - Vành đai III trên cao - Phạm Văn Đồng - cầu Thăng Long - Võ Văn Kiệt hoặc theo tuyến Pháp Vân - cầu Thanh Trì - QL1B - QL5 - Lý Sơn - cầu Đông Trù - Trường Sa - Hoàng Sa - Võ Văn Kiệt đi các tỉnh  Đi các tỉnh phía Tây thành phố (Phú Thọ  Hòa Bình  Sơn La  Điện Biên…)  Pháp Vân - Vành đai III trên cao - Đại lộ Thăng Long (hoặc QL32) hoặc theo tuyến  Pháp Vân - Ngọc Hồi - Phan Trọng Tuệ - Phúc La - Văn Phú - Lê Trọng Tấn - Đại lộ Thăng Long (hoặc từ Lê Trọng Tấn - Tỉnh lộ 70 đi ra QL32) đi các tỉnh      Hạn chế phương tiện hoạt động trên địa bàn quận Hoàn Kiếm gồm các tuyến đường  Trần Nhật Duật  Trần Quang Khải  Đê 401  Phạm Ngũ Lão  Đặng Thái Thân  Lê Thánh Tông  Tràng Tiền  Ngô Quyền  Lý Thường Kiệt  Phan Chu Trinh  Hai Bà Trưng  Quán Sứ  Tràng Thi  Phan Bội Châu  Hàng Bài  Hàng Khay  Lê Thái Tổ  Lê Phụng Hiểu  Trần Khánh Dư  Hạn chế phương tiện hoạt động trên địa bàn quận Ba Đình  Tây Hồ gồm các tuyến đường  Nguyễn Chí Thanh  Kim Mã  Nguyễn Thái Học  Chu Văn An  Điện Biên Phủ  Độc Lập  Hoàng Văn Thụ  Hùng Vương  Hoàng Diệu  Lê Hồng Phong  Trần Phú  Thanh Niên  An Dương Vương  Âu Cơ  Nghi Tàm  Yên Phụ  Bưởi  Đào Tấn  Võ Chí Công  vành đai II  Hạn chế phương tiện hoạt động trên địa bàn quận Đống Đa gồm các tuyến đường  Nguyễn Chí Thanh  Láng  Hạn chế phương tiện hoạt động trên địa bàn quận Cầu Giấy  Nam Từ Liêm gồm các tuyến đường  Trần Duy Hưng  Đại lộ Thăng Long (phần đường tiếp giáp với trung tâm Hội nghị Quốc gia  đoạn từ Trần Duy Hưng đến Lê Quang Đạo)  Đỗ Đức Dục  Miếu Đầm  Mễ Trì  Lê Quang Đạo  Hạn chế phương tiện hoạt động trên địa bàn huyện Đông Anh  Sóc Sơn  Đường Võ Nguyên Giáp  Các phương tiện vào trung tâm Thành phố hạn chế đi qua địa bàn các quận Hoàn Kiếm  Ba Đình  Tây Hồ  Đống Đa  Cầu Giấy  Nam Từ Liêm  cầu Chương Dương  Nhật Tân (theo hướng vào trung tâm thành phố)  Các phương tiện đi từ các tỉnh phía Đông thành phố (Quảng Ninh  Hải Dương  Thái Bình  Hưng Yên…) đi các tỉnh phía Bắc (Lào Cai  Vĩnh Phúc…) hoặc các tỉnh phía Tây thành phố (Phú Thọ  Hòa Bình  Sơn La  Điện Biên…) và ngược lại  Đi các tỉnh phía Bắc thành phố (Lào Cai  Vĩnh Phúc…)  QL5 - Lý Sơn - cầu Đông Trù - Trường Sa - Hoàng Sa - Võ Văn Kiệt đi các tỉnh  Đi các tỉnh phía Tây thành phố (Phú Thọ  Hòa Bình  Sơn La  Điện Biên…)  QL5 - QL1 - cầu Thanh Trì - Vành đai III trên cao - QL32 hoặc QL5 - Lý Sơn - cầu Đông Trù - Trường Sa - Hoàng Sa - Võ Văn Kiệt - cầu Thăng Long - Phạm Văn Đồng - QL32 đi các tỉnh  Các phương tiện đi từ phía Nam thành phố (Nam Định  Hà Nam  Ninh Bình…) đi các tỉnh phía Bắc (Lào Cai  Vĩnh Phúc…) hoặc các tỉnh phía Tây Thành phố (Phú Thọ  Hòa Bình  Sơn La  Điện Biên…) theo các hướng  Đi các tỉnh phía Bắc thành phố (Lào Cai  Vĩnh Phúc…)  Pháp Vân - Vành đai III trên cao - Phạm Văn Đồng - cầu Thăng Long - Võ Văn Kiệt hoặc Pháp Vân - cầu Thanh Trì - QL1B - QL5 - Lý Sơn - cầu Đông Trù - Trường Sa - Hoàng Sa - Võ Văn Kiệt đi các tỉnh và ngược lại  Đi các tỉnh phía Tây Thành phố (Phú Thọ  Hòa Bình  Sơn La  Điện Biên…)  Pháp Vân - Vành đai III trên cao - QL32 hoặc Pháp Vân - Ngọc Hồi - Phan Trọng Tuệ - Phúc La - Văn Phú - Lê Trọng Tấn - Tỉnh lộ 70 - Quốc lộ 32 đi các tỉnh và ngược lại  Riêng xe ô tô tải có trọng lượng toàn bộ cho phép tham gia giao thông từ 10 tấn trở lên từ phía Nam đi phía Bắc thành phố đi theo tuyến  Pháp Vân - Ngọc Hồi - Phan Trọng Tuệ - Phúc La - Văn Phú - Lê Trọng Tấn - Tỉnh lộ 70 và ngược lại  Công an TP Hà Nội đề nghị tất cả các phương tiện khi tham gia giao thông phải nghiêm chỉnh chấp hành Luật Giao thông đường bộ  khi gặp các xe được quyền ưu tiên đang phát tín hiệu ưu tiên đi làm nhiệm vụ phải khẩn trương đi sát phần đường bên phải  chủ động đi vào các các đường tránh gần nhất hoặc dừng hẳn lại nhường đường cho đoàn xe ưu tiên "}