{"url": "http://www.24h.com.vn/tin-tuc-trong-ngay/thong-tin-moi-ve-tam-ve-trung-jackpot-395-ti-dong-cua-vietlott-c46a915841.html", "title": "Thông tin mới về tấm vé trúng jackpot 39 5 tỉ đồng của Vietlott", "description": " Vietlott vừa công bố những thông tin cụ thể hơn của tấm vé trúng giải ", "time": "2017-11-06 13:26:00", "content": "Kết quả kỳ quay 203 của chương trình xổ số Mega 6/45  Tại kỳ quay số mở thưởng thứ 203 vào ngày 5/11  Công ty Xổ số điện toán Việt Nam - Vietlott xác định  giải jackpot sản phẩm Mega 6/45 trị giá hơn 39 5 tỉ đồng đã có chủ nhờ bộ số 03 - 17 - 38 - 39 - 41 - 44  Xác định từ hệ thống  Vietlott xác định chỉ có duy nhất 1 vé trúng giải jackpot này  Chiếc vé được phát hành tại một điểm bán hàng trên đường Bùi Hữu Nghĩa  phường 2 quận Bình Thạnh  TP HCM lúc 14h22 ngày 3/11  Với giải thưởng hơn 39 5 tỉ đồng nói trên  chủ nhân của tấm vé may mắn sẽ thực nhận khoảng 35 55 tỉ đồng sau khi đóng thuế thu nhập cá nhân gần 4 tỉ đồng theo quy định  Tuy nhiên  cho tới lúc này  chủ nhân của jackpot  khủng  vẫn chưa xuất hiện  Trước đó  kỷ lục giá trị jackpot - Mega 6/45 là hơn 159 tỉ đồng (kỳ quay 69  ngày 25/12/2016)  tuy nhiên  giải jackpot này có tới 2 người cùng trúng nên mỗi người nhận được gần 80 tỉ đồng trước thuế  Còn kỷ lục jackpot dành cho một người là gần 132 tỉ đồng (kỳ quay 156  ngày 19/7/2017)  thuộc về bà H  ngụ tại huyện Xuyên Mộc  tỉnh Bà Rịa - Vũng Tàu  Tất cả những nhân vật nói trên đều đã đeo mặt nạ nhận giải "}