{"url": "https://thanhnien.vn/kinh-doanh/ha-noi-sap-dua-xe-buyt-2-tang-city-tour-phuc-vu-du-lich-897484.html", "title": "Hà Nội sắp đưa xe buýt 2 tầng City tour phục vụ du lịch", "description": "Sở GTVT Hà Nội vừa có văn bản báo cáo UBND TP Hà Nội về kế hoạch triển khai thí điểm tuyến xe 2 tầng City tour phục vụ phát triển du lịch ", "time": "2017-11-07 09:16:00", "content": "Theo Giám đốc Sở GTVT TP Hà Nội Vũ Văn Viện  trên cơ sở khảo sát hiện trường  Sở GTVT  Sở Du lịch và Tổng công ty vận tải Hà Nội (Transerco) thống nhất lộ trình hoạt động theo 2 khung thời gian  Cụ thể  đối với ngày trong tuần  lộ trình tuyến cơ bản từ Nhà hát Lớn - Tràng Tiền - đê Yên Phụ - Thanh Niên - Hùng Vương - Nguyễn Thái Học - Lý Thường Kiệt - Nhà hát Lớn  đối với ngày cuối tuần (tổ chức tuyến phố đi bộ quanh khu vực Bờ Hồ) lộ trình tương tự nhưng bỏ qua các đường cấm phương tiện  Sở Du lịch cũng phối hợp với các sở  ngành khảo sát  thống nhất chọn 14 điểm  dừng đỗ trả khách du lịch trên tuyến đường tham quan  gồm  Nhà hát Lớn  Bưu điện Hà Nội  quảng trường Đông Kinh Nghĩa Thục  Nhà thờ lớn  Lăng Chủ tịch Hồ Chí Minh  "}