{"url": "https://vnexpress.net/tin-tuc/cuoi/anh/xin-chuyen-lop-vi-nho-bo-mien-man-3633998.html", "title": "             Xin chuyển lớp vì 'nhớ bồ miên man'                     ", "description": "Không thể ngủ được vì xa cách người yêu  nữ sinh làm đơn xin chuyển lớp để thỏa niềm mong nhớ  ", "time": "2017-09-02 00:01:00", "content": " Bên cạnh đó thì nghỉ học để chăm người yêu ốm  chuyển chỗ vì thích bạn  cũng là những lý do viết đơn hài hước và lãng mạn của học trò     'Kính gửi  Cô giáo bộ môn Toán Em tên là  Em làm đơn này xin cô cho em nghỉ học buổi sáng nay  Lý do  Người yêu em bị ốm nặng  Em xin hứa sẽ hoàn thành những yêu cầu cô đề ra trong buổi hợc sáng ngày hôm nay  Em xin chân thành cảm ơn'    Kính gửi  Thầy giáo chủ nhiệm và thầy giáo bộ môn Tên em là  Lý do em viết giấy nghỉ học như sau  Hôm nay ngày 28/11/2016  gia đình có tổ chức hỏi vợ cho em nên em viết giấy này kính lên thầy giáo chủ nhiệm  thầy giáo bộ môn cho phép em nghỉ học hôm nay  ngày 28/11/2016  Cuối cùng em xin chân thành cảm ơn  Xem thêm      "}