{"url": "http://dantri.com.vn/the-gioi/giai-ma-bien-so-dac-biet-cua-xe-quai-thu-cho-tong-thong-trump-20171110113916919.htm", "title": "     Giải mã biển số đặc biệt của xe  Quái thú  chở Tổng thống Trump", "description": "     Giải mã biển số đặc biệt của xe  Quái thú  chở Tổng thống Trump", "time": "2017-11-10 12:24:00", "content": "     Theo Politico  biển số của chiếc xe Cadillac One được mệnh danh  Quái thú  dành cho Tổng thống Mỹ là dãy số 800-002  Bên trên dãy số là dòng chữ    để biểu thị nơi đăng ký của chiếc xe ở thủ đô Washington D C  Tất cả các xe của Tổng thống Mỹ đều đăng ký ở Washington D C  Bên dưới dãy số là dòng chữ   (Đóng thuế những không có dân biểu)  Với dòng chữ này  biển số xe chuyên dụng của Tổng thống Mỹ mang ý nghĩa đề cập đến việc Washington D C đóng thuế nhưng không có dân biểu có quyền bỏ phiếu ở quốc hội      Washington D C chủ yếu nằm trên phần đất của bang Maryland và Virginia nhưng không thuộc sở hữu của bang nào nên phải chịu quy chế thành phố liên bang  cư dân của Washington vẫn phải đóng thuế thu nhập như các bang khác của Mỹ  Tuy nhiên  Hiến pháp Mỹ quy định  chỉ các bang mới có đại diện tại Hạ viện và Thượng viện Mỹ  nên Washington D C không có đại diện có quyền bầu cử tại Quốc hội  mà chỉ có một đại biểu không có quyền bầu cử trong Hạ viện  Biển số xe mang thông điệp trên bắt đầu được Tổng thống Bill Clinton sử dụng năm 2000  Tuy nhiên  đến khi Tổng thống Bush nhậm chức  ông đã không sử dụng loại biển số đó  Đến nhiệm kỳ thứ hai  Tổng thống Barack Obama quyết định sử dụng lại biển số có in những thông điệp này  Ông Obama là một trong những tổng thống ủng hộ chủ trương vì quyền lợi của Washington D C tại quốc hội  Hiện nay  Tổng thống Trump vẫn giữ biển số này cho  Quái thú   "}