{"url": "http://www.24h.com.vn/bong-da/chelsea-dau-mu-conte-nhan-toi-hau-thu-thua-mourinho-se-bi-tram-c48a915431.html", "title": "Chelsea đấu MU  Conte thắng  Abramovich vẫn sẽ sa thải ", "description": " Mối quan hệ giữa ông chủ Abramovich và HLV Conte đã đổ vỡ và dự kiến nhà cầm quân người Italia sẽ không thể giữ ghế dù có thắng được MU ", "time": "2017-11-04 11:04:00", "content": "Tình hình Chelsea trước trận gặp MU đang trở nên rối ren  Tờ Marca không lâu sau khi đưa tin Antonio Conte sẽ bị sa thải nếu thua MU thì mới đây lại cho biết dù  The Blues  có chiến thắng trong trận cầu  Super Sunday  cuối mùa nhà cầm quân người Italia vẫn sẽ bị mời ra khỏi Stamford Bridge  Marca khẳng định Conte gần như chắc chắn sẽ mất việc cuối mùa giải này Marca cho biết mối quan hệ giữa Conte và ông chủ Roman Abramovich đã ở vào tình thế không thể hàn gắn nổi  Lý do chính là bởi Conte đã công khai chỉ trích giám đốc kỹ thuật Michael Emenalo  người phụ trách chuyển nhượng của CLB và cũng là  cánh tay mặt  của Abramovich để giám sát các hoạt động của đội bóng  Conte từ lúc đến dẫn dắt Chelsea đã có mâu thuẫn với một số cầu thủ mà đáng kể nhất là trường hợp của Diego Costa  người đã bị CLB bán đi một cách bất đắc dĩ dù Abramovich được cho là muốn giữ Costa  Michy Batshuayi gia nhập đội bóng mùa hè 2016 nhưng Conte không muốn mua tiền đạo này  dẫn tới chân sút người Bỉ đã hơn 1 năm qua mài mòn ghế dự bị  Những vấn đề này đã khiến Abramovich đi tới chỗ quyết định từ giờ sẽ không liên lạc với Conte trực tiếp nữa  thay vào đó trợ lý của Abramovich và cũng là một giám đốc ở CLB  bà Marina Granovskaia  sẽ thay mặt ông chủ người Nga nói chuyện với Conte  Marca cho biết bắt đầu từ lúc này Abramovich đã khởi động kế hoạch tìm người thay thế Conte  và HLV người Italia sẽ chỉ được cho giữ ghế để làm xong việc cho tới hết mùa giải trước khi tiến hành bàn giao  Xưa nay  người hâm mộ quen với hình ảnh Roman Abramovich dự khán các trận đấu của Chelsea  Nhưng một khi ông xuất hiện trên sân tập Cobham thì y như rằng  The Blues  có biến  Đó hầu như là giai đoạn  đạt thành tích không tốt  Abramovich thị phạm để cảnh báo HLV trưởng hoặc ra tối hậu thư  Chủ tịch Abramovich đặt Conte vào vùng nguy hiểm Cuối năm 2015  chỉ ít ngày sau khi Abramovich có mặt ở Cobham  HLV Jose Mourinho liền bị sa thải sau chuỗi phong độ nghèo nàn  Tháng 9 năm ngoái  tỷ phú người Nga cũng gác bỏ trăm công nghìn việc xuống sân tập Chelsea thị phạm sau màn khởi đầu kém cỏi và tạo áp lực với HLV Conte hãy nhanh chóng chứng tỏ khả năng  May mắn  tháng ngày tiếp theo  Conte đưa Chelsea đi đúng hướng và vô địch    Sang mùa này  Chelsea lại có sự khởi đầu không như ý  Tại Ngoại hạng Anh  công cuộc bảo vệ ngôi vương của họ rất khó khăn khi đang thua kém Man City tới 9 điểm  Ở đấu trường Champions League  Chelsea cũng vừa thua thảm Roma 0-3 và mất ngôi đầu bảng C  Tình hình bất ổn của Chelsea buộc ông chủ Abramovich phải ra mặt  Mới đây  cánh phóng viên ở Anh bất ngờ thấy vị tỷ phú này tới sân tập Cobham  Hành động vốn được coi là bất thường này của Abramovich làm dấy lên tin đồn rằng Chelsea đã nghiêm túc xem xét khả năng sa thải HLV Conte  Tờ Mirror cho hay  Abramovich sẵn sàng xuống tay  trảm  Conte nếu nhà cầm quân người Italia tiếp tục gây thất vọng ở màn tiếp đón MU vào đêm mai (23h30  5/11)  Trước đó  tờ Marca từng tiết lộ  Abramovich đã ra quyết định sa thải Conte vào cuối mùa này  Mối quan hệ giữa   trong vài tuần qua được mô tả là không tốt đẹp  Khó khăn bủa vây cựu chiến lược gia của Juventus khi các ngôi sao Chelsea cũng bắt đầu khó chịu với sự cứng nhắc trong khâu huấn luyện "}