{"url": "https://vnexpress.net/tin-tuc/phap-luat/tham-phan-o-mien-tay-bi-canh-cao-vi-danh-phu-nu-3648795.html", "title": "             Thẩm phán ở miền Tây bị cảnh cáo vì đánh phụ nữ                     ", "description": "Hơn ba tháng sau khi tát người phụ nữ tại khách sạn  Chánh tòa Hình sự TAND tỉnh Cà Mau bị cảnh cáo ", "time": "2017-09-30 00:00:00", "content": " TAND tỉnh Cà Mau vừa kỷ luật về mặt chính quyền đối với ông Lê Thường Vụ - Chánh tòa Hình sự - bằng hình thức cảnh cáo  tiếp tục xem xét xử lý về mặt Đảng do vi phạm đạo đức  lối sống  Hồi tháng 6  Công an phường 7  TP Cà Mau lập biên bản việc ông Vụ đánh vào mặt người phụ nữ khi xảy ra mâu thuẫn  Ông Vụ cũng thừa nhận trong lúc nóng giận  có chửi thề và đánh người  Người phụ nữ sau đó tố cáo với TAND tỉnh Cà Mau  nhận  có quan hệ nam nữ  nhiều năm trước với ông Vụ  Tối hôm đó bà phát hiện ông này vào khách sạn với người phụ nữ khác nên xông đến gọi cửa để  làm cho rõ  Trong lúc cự cãi bà bị ông Vụ hành hung  TAND tỉnh Cà Mau xác định ông Vụ xâm phạm thân thể người khác là có và việc này gây mất uy tín cơ quan cũng như cá nhân ông Vụ  Chánh toà Hình sự cũng có nhiều tin nhắn với người tố cáo  cách xưng hô  tình cảm  chưa đúng phẩm chất  đạo đức  lối sống công chức  "}