{"url": "https://vnexpress.net/tin-tuc/cuoi/tieu-pham/tai-sao-do-ngu-phu-nu-in-hoa-dan-ong-lai-ke-soc-hot-nhat-tuan-3658040.html", "title": "             'Tại sao đồ ngủ phụ nữ in hoa  đàn ông lại kẻ sọc?' hot nhất tuần                     ", "description": "Sự khác biệt giữa đồ ngủ nam và nữ ẩn chứa ý nghĩa mà chỉ người đã lập gia đình mới thấu hiểu  ", "time": "2017-10-21 00:02:00", "content": " Bên cạnh đó thì mua bánh mỳ giữa trời giông bão  thư tình của bác sĩ  cũng là những truyện cười được xem nhiều nhất trong tuần    Hai vợ chồng dạo trong cửa hàng quần áo ngủ  người vợ hỏi  - Anh này  em phát hiện ra một chuyện lạ lắm  - Chuyện gì? - người chồng nhướng mày hỏi  - Em phát hiện đồ ngủ của phụ nữ thì thêu hoa  màu sắc rực rỡ  nhưng đồ ngủ của đàn ông đa số chỉ là pajama kẻ sọc  Tại sao thế anh nhỉ? Người chồng mỉm cười  - Đơn giản mà  Vì ban đêm đối với phụ nữ là mùa xuân  còn đối với đàn ông là lao động khổ sai! - !?!   - Ông có vợ rồi phải không? Người đàn ông cáu gắt đáp  - Thì đúng là có vợ rồi  Bộ bà nghĩ  mẹ tôi nỡ sai tôi đi mua một ổ bánh mỳ trong trời giông bão như thế này sao? - !?!   - Này  cô đến khám gì? - Dạ  em không khám ạ! Em đến nhờ bác sĩ tý việc  - Xin cô cứ nói  - Dạ  em nhờ anh đọc hộ bức thư của người yêu em mới gửi về  - Thư của cô sao lại nhờ tôi đọc  cô không biết chữ à  - Dạ  em biết chữ  nhưng vẫn không đọc được thư của anh ấy  Vì người yêu em cũng là bác sĩ nên mới đến nhờ anh  - !!!   - Trong đám ta đây ai là người sợ vợ nhất? Chưa ai dám đáp thì ông cụ lớn tuổi nhất đã nhận ngay  - Kể sợ thì tôi đây sợ nhất! Mọi người lấy làm lạ mới hỏi  - Cụ có vợ đâu mà sợ? - Tôi sợ đến nỗi không dám lấy vợ    - Ông xem kìa  tóc ông bạc hết rồi còn gì? Ông chồng thở dài  - Bà xem hộ tôi mấy cái răng này đã long chưa? - Cũng long hết cả rồi  Ông chồng nghe thế liền tươi cười  - Mai tôi với bà chia tay thôi nhé! Ngày xưa mình hẹn nhau chung sống đến đầu bạc răng long  tôi chờ mãi mới đến ngày này! - !!!  "}